{
  "$schema": "https://mintlify.com/schema.json",
  "name": "Layouts.dev",
  "logo": {
    "dark": "/logo/logomark_dark.svg",
    "light": "/logo/wordmark_logo.svg"
  },
  "favicon": "/logo/layouts-logo-transparent.svg",
  "colors": {
    "primary": "#171717",
    "light": "#F4F3F1",
    "dark": "#171717",
    "anchors": {
      "from": "#171717",
      "to": "#453D3D"
    }
  },
  "topbarLinks": [
    {
      "name": "Help",
      "url": "mailto:hi@mintlify.com"
    }
  ],
  "topbarCtaButton": {
    "name": "Sign In",
    "url": "https://dashboard.mintlify.com"
  },
  "anchors": [
    {
      "name": "Docs",
      "icon": "book-open-cover",
      "url": "https://mintlify.com/docs"
    },
    {
      "name": "Community",
      "icon": "discord",
      "url": "https://mintlify.com/community"
    },
    {
      "name": "Blog",
      "icon": "book",
      "url": "https://mintlify.com/blog"
    }
  ],
  "navigation": [
    {
      "group": "Layouts 101",
      "pages": [
        "essentials/introduction",
        "essentials/Layouts syntax",
        "essentials/export",
        "essentials/help"
      ]
    },
    {
      "group": "Account setup",
      "pages": [
        "Editor",
        "Docs",
        "Preview",
        "Code"
      ]
    },
    {
      "group": "Components",
      "pages": [
        "Accordion",
        "Alert",
        "Alert Dialog",
        "Aspect Ratio",
        "Avatar",
        "Badge",
        "Button",
        "Calendar",
        "Card",
        "Carousel",
        "Checkbox",
        "Collapsible",
        "Combobox",
        "Command",
        "Context Menu",
        "Data Table",
        "Date Picker",
        "Dialog",
        "Drawer",
        "Dropdown Menu",
        "Form",
        "Hover Card",
        "Input",
        "Label",
        "Menubar",
        "Navigation Menu",
        "Pagination",
        "Popover",
        "Progress",
        "Radio Group",
        "Resizable",
        "Scroll Area",
        "Select",
        "Separator",
        "Sheet",
        "Slider",
        "Sonner",
        "Switch",
        "Table",
        "Tabs",
        "Textarea"
        "Toast",
        "Toggle",
        "Toggle Group",
        "Tooltip"
      ]
    }
  ],
  "footerSocials": {
    "twitter": "https://twitter.com/mintlify",
    "github": "https://github.com/mintlify",
    "linkedin": "https://www.linkedin.com/company/mintsearch"
  }
}